{
  "checklists": [
    {
      "ticket": "123",
      "status": "in_progress",
      "createdBy": "MZ",
      "createdAt": "2026-07-12T04:29:36.760Z",
      "updatedAt": "2026-07-12T04:29:52.266Z",
      "doneCount": 2,
      "totalCount": 5
    },
    {
      "ticket": "124",
      "status": "completed",
      "createdBy": "MZ",
      "createdAt": "2026-07-12T04:30:22.024Z",
      "updatedAt": "2026-07-12T04:30:39.015Z",
      "doneCount": 5,
      "totalCount": 5
    },
    {
      "ticket": "444",
      "status": "in_progress",
      "createdBy": "MZ",
      "createdAt": "2026-07-12T14:00:18.588Z",
      "updatedAt": "2026-07-12T14:00:29.115Z",
      "doneCount": 1,
      "totalCount": 5
    },
    {
      "ticket": "MICHAEL-ZAGAME-666",
      "status": "in_progress",
      "createdBy": "Michael Zagame",
      "createdAt": "2026-07-15T11:00:45.708Z",
      "updatedAt": "2026-07-15T11:02:08.052Z",
      "doneCount": 12,
      "totalCount": 30
    }
  ]
}